loglama/__init__.py
loglama/api/__init__.py
loglama/api/server.py
loglama/cli/__init__.py
loglama/cli/commands/__init__.py
loglama/cli/commands/diagnostic_commands.py
loglama/cli/commands/env_commands.py
loglama/cli/commands/logs_commands.py
loglama/cli/commands/project_commands.py
loglama/cli/commands/update_loggers.py
loglama/cli/diagnostics.py
loglama/cli/main.py
loglama/cli/utils.py
loglama/cli/web_viewer.py
loglama/collectors/__init__.py
loglama/collectors/log_collector.py
loglama/collectors/scheduled_collector.py
loglama/compat.py
loglama/config/__init__.py
loglama/config/env_loader.py
loglama/core/__init__.py
loglama/core/env_manager.py
loglama/core/logger.py
loglama/core/simple_logger.py
loglama/db/__init__.py
loglama/db/handlers.py
loglama/db/models.py
loglama/decorators/__init__.py
loglama/decorators/auto_fix.py
loglama/decorators/diagnostics.py
loglama/decorators/error_handling.py
loglama/diagnostics/__init__.py
loglama/diagnostics/health.py
loglama/diagnostics/troubleshoot.py
loglama/formatters/__init__.py
loglama/formatters/colored_formatter.py
loglama/formatters/json_formatter.py
loglama/handlers/__init__.py
loglama/handlers/api_handler.py
loglama/handlers/memory_handler.py
loglama/handlers/rotating_file_handler.py
loglama/handlers/sqlite_handler.py
loglama/middleware/__init__.py
loglama/scripts/__init__.py
loglama/scripts/apply_decorators.py
loglama/scripts/diagnose_ansible.py
loglama/scripts/diagnose_project.py
loglama/scripts/loglama_bash.sh
loglama/utils/__init__.py
loglama/utils/auto_fix.py
loglama/utils/context.py
loglama/utils/filters.py
loglama/utils/helpers.py
loglama/web/__init__.py
loglama/web/app.py
loglama/web/static/__init__.py
loglama/web/static/css/__init__.py
loglama/web/static/css/style.css
loglama/web/static/js/__init__.py
loglama/web/static/js/app.js
loglama/web/templates/__init__.py
loglama/web/templates/index.html
loglama/web/templates/services.html
loglama-0.1.17.dist-info/LICENSE
loglama-0.1.17.dist-info/METADATA
loglama-0.1.17.dist-info/WHEEL
loglama-0.1.17.dist-info/RECORD
