Metadata-Version: 2.3
Name: loglama
Version: 0.1.17
Summary: Powerful logging and debugging utility for PyLama ecosystem
License: Apache-2.0
Author: Tom Sapletta
Author-email: info@softreck.dev
Requires-Python: >=3.10,<4.0
Classifier: License :: OSI Approved :: Apache Software License
Classifier: Programming Language :: Python :: 3
Classifier: Programming Language :: Python :: 3.10
Classifier: Programming Language :: Python :: 3.11
Classifier: Programming Language :: Python :: 3.12
Classifier: Programming Language :: Python :: 3.13
Requires-Dist: click (>=8.2.1,<9.0.0)
Requires-Dist: colorama (>=0.4.6,<0.5.0)
Requires-Dist: flask (>=3.1.1,<4.0.0)
Requires-Dist: pydantic (>=2.11.4,<3.0.0)
Requires-Dist: python-dotenv (>=1.1.0,<2.0.0)
Requires-Dist: requests (>=2.32.3,<3.0.0)
Requires-Dist: rich (>=14.0.0,<15.0.0)
Requires-Dist: sqlalchemy (>=2.0.41,<3.0.0)
Requires-Dist: structlog (>=25.3.0,<26.0.0)
